wagtaildraftsharing/__init__.py
wagtaildraftsharing/actions.py
wagtaildraftsharing/apps.py
wagtaildraftsharing/forms.py
wagtaildraftsharing/models.py
wagtaildraftsharing/settings.py
wagtaildraftsharing/snippets.py
wagtaildraftsharing/urls.py
wagtaildraftsharing/utils.py
wagtaildraftsharing/views.py
wagtaildraftsharing/wagtail_hooks.py
wagtaildraftsharing/migrations/0001_initial.py
wagtaildraftsharing/migrations/0002_alter_wagtaildraftsharinglink_created_by.py
wagtaildraftsharing/migrations/0003_alter_wagtaildraftsharinglink_revision.py
wagtaildraftsharing/migrations/__init__.py
wagtaildraftsharing/static/wagtaildraftsharing/js/wagtaildraftsharing.js
wagtaildraftsharing/static/wagtaildraftsharing/js/wagtaildraftsharing_controller.js
wagtaildraftsharing/templates/wagtailadmin/generic/history/action_cell.html
wagtaildraftsharing/templates/wagtailadmin/pages/revisions/_actions.html
wagtaildraftsharing/templates/wagtaildraftsharing/action_menu_item.html
wagtaildraftsharing/tests/__init__.py
wagtaildraftsharing/tests/settings.py
wagtaildraftsharing/tests/test_models.py
wagtaildraftsharing/tests/test_views.py
wagtaildraftsharing/tests/test_wagtail_hooks.py
wagtaildraftsharing/tests/urls.py
wagtaildraftsharing-0.3.0.dist-info/licenses/LICENSE
wagtaildraftsharing-0.3.0.dist-info/METADATA
wagtaildraftsharing-0.3.0.dist-info/WHEEL
wagtaildraftsharing-0.3.0.dist-info/top_level.txt
wagtaildraftsharing-0.3.0.dist-info/RECORD
