Metadata-Version: 2.4
Name: wagtaildraftsharing
Version: 0.3.0
Summary: Share wagtail drafts with private URLs.
Author-email: Shohan Dutta Roy <shohanduttaroy99@gmail.com>
Maintainer-email: Steve Jalim <stevejalim@mozilla.com>
License: CC0
Project-URL: Homepage, https://github.com/KIRA009/wagtaildraftsharing
Project-URL: Bug Reports, https://github.com/KIRA009/wagtaildraftsharing/issues
Project-URL: Source, https://github.com/KIRA009/wagtaildraftsharing
Classifier: Framework :: Django
Classifier: Framework :: Django :: 3.2
Classifier: Framework :: Django :: 4.2
Classifier: Framework :: Django :: 5.1
Classifier: Framework :: Wagtail
Classifier: Framework :: Wagtail :: 5
Classifier: Framework :: Wagtail :: 6
Classifier: License :: CC0 1.0 Universal (CC0 1.0) Public Domain Dedication
Classifier: License :: Public Domain
Classifier: Programming Language :: Python
Classifier: Programming Language :: Python :: 3
Requires-Python: >=3.9
License-File: LICENSE
Requires-Dist: wagtail>=5.1
Provides-Extra: testing
Requires-Dist: coverage[toml]; extra == "testing"
Requires-Dist: tox; extra == "testing"
Requires-Dist: tox-gh-actions; extra == "testing"
Requires-Dist: wagtail-factories; extra == "testing"
Requires-Dist: freezegun==1.5.1; extra == "testing"
Dynamic: license-file
